CHANGES.rst
LICENSE
MANIFEST.in
Makefile
README.rst
setup.py
tests/conftest.py
tests/model_fixtures.py
tests/test_basic.py
torch_inspect/__init__.py
torch_inspect/inspect.py
torch_inspect.egg-info/PKG-INFO
torch_inspect.egg-info/SOURCES.txt
torch_inspect.egg-info/dependency_links.txt
torch_inspect.egg-info/requires.txt
torch_inspect.egg-info/top_level.txt
torch_inspect.egg-info/zip-safe