Metadata-Version: 1.1
Name: torch-inspect
Version: 0.0.3
Summary: Utility functions that prints a summary of a model.
Home-page: https://github.com/jettify/pytorch-inspect
Author: Nikolay Novik
Author-email: nickolainovik@gmail.com
License: Apache 2
Download-URL: https://pypi.org/project/torch-inspect/
Keywords: torch-inspect,pytorch
Platform: POSIX
Classifier: License :: OSI Approved :: Apache Software License
Classifier: Intended Audience :: Developers
Classifier: Programming Language :: Python :: 3
Classifier: Programming Language :: Python :: 3.6
Classifier: Programming Language :: Python :: 3.7
Classifier: Operating System :: OS Independent
Classifier: Development Status :: 3 - Alpha
